code_capture.py
code_capture-0.1.3.dist-info/METADATA
code_capture-0.1.3.dist-info/WHEEL
code_capture-0.1.3.dist-info/licenses/LICENSE.txt
code_capture-0.1.3.dist-info/RECORD
