Metadata-Version: 2.4
Name: code-capture
Version: 0.1.3
Summary: Capture code blocks while executing them
Author: Peter Somhorst, Grayden Shand
License-File: LICENSE.txt
Requires-Python: >=3.10
Requires-Dist: bunch-py3>=2.0.0
